fm/__init__.py
fm/__init__.pyi
fm/fm.abi3.so
fm/py.typed
fm_rs-0.1.4.dist-info/METADATA
fm_rs-0.1.4.dist-info/WHEEL
fm_rs-0.1.4.dist-info/RECORD
