Metadata-Version: 2.4
Name: fm-rs
Version: 0.1.4
Classifier: Development Status :: 4 - Beta
Classifier: Intended Audience :: Developers
Classifier: License :: OSI Approved :: MIT License
Classifier: Operating System :: MacOS :: MacOS X
Classifier: Programming Language :: Python :: 3
Classifier: Programming Language :: Python :: 3.10
Classifier: Programming Language :: Python :: 3.11
Classifier: Programming Language :: Python :: 3.12
Classifier: Programming Language :: Python :: 3.13
Classifier: Programming Language :: Rust
Classifier: Topic :: Scientific/Engineering :: Artificial Intelligence
Classifier: Environment :: MacOS X
Summary: Python bindings for Apple's FoundationModels.framework
Keywords: apple,ai,llm,foundation-models,apple-intelligence
License-Expression: MIT
Requires-Python: >=3.10
Project-URL: Homepage, https://github.com/blacktop/fm-rs
Project-URL: Issues, https://github.com/blacktop/fm-rs/issues
Project-URL: Repository, https://github.com/blacktop/fm-rs
